[
  {
    "id": "france24",
    "name": "France 24",
    "category": "International",
    "logo": "",
    "servers": [
      {
        "url": "https://app.ncare.live/c3VydmVyX8RpbEU9Mi8xNy8yMDE0GIDU6RgzQ6NTAgdEoaeFzbF92YWxIZTO0U0ezN1IzMyfvcGVMZEJCTEFWeVN3PTOmdFsaWRtaW51aiPhnPTI2/fr24.stream/playlist.m3u8",
        "latency": 165,
        "quality": "",
        "stability": 0.9714285714285714,
        "type": "hls"
      }
    ]
  },
  {
    "id": "france24english",
    "name": "France 24 English",
    "category": "International",
    "logo": "",
    "servers": [
      {
        "url": "https://live.france24.com/hls/live/2037218-b/F24_EN_HI_HLS/master_2300.m3u8",
        "latency": 494,
        "quality": "HD",
        "stability": 1,
        "type": "hls"
      }
    ]
  },
  {
    "id": "globalpunjab",
    "name": "Global Punjab",
    "category": "International",
    "logo": "https://i.imgur.com/WDLqcWW.png",
    "epg_id": "GlobalPunjab.in@SD",
    "servers": [
      {
        "url": "https://server.livelegitpro.in/globalpunjab/globalpunjab/index.m3u8",
        "latency": 663,
        "quality": "FHD",
        "stability": 1,
        "type": "hls"
      }
    ]
  },
  {
    "id": "globaltv",
    "name": "Global Tv",
    "category": "International",
    "logo": "https://tvassets.roarzone.info/images/global-tv.png",
    "servers": [
      {
        "url": "https://tvsen6.aynascope.net/globaltvhd/index.m3u8?e=1773790870&u=78be6644-0a65-48ec-81a4-089ac65a2619&token=3fc49d3f7a6cbf18a11abb06c7f7038b",
        "latency": 1097,
        "quality": "HD",
        "stability": 1,
        "type": "hls"
      },
      {
        "url": "https://edge2.roarzone.info:8447/roarzone/edge3/global-tv/index.m3u8?token=dc5a8960f5dd31fa30065df7a27419cd39fbe01e-a5f176e55a4f926e703282da0c25144c-1773787230-1773783630",
        "latency": 1121,
        "quality": "",
        "stability": 1,
        "type": "hls"
      }
    ]
  },
  {
    "id": "harvestusa",
    "name": "Harvest USA",
    "category": "International",
    "logo": "https://www.lyngsat.com/logo/tv/hh/harvest_tv_in_usa.png",
    "epg_id": "HarvestUSA.in@SD",
    "servers": [
      {
        "url": "https://7mbd4ogkr3gx-hls-live.wmncdn.net/harvestusa/d57ffba6564caea2fee3f4085f19a098.sdp/playlist.m3u8",
        "latency": 1031,
        "quality": "SD",
        "stability": 0.8082191780821918,
        "type": "hls"
      }
    ]
  },
  {
    "id": "ibtvusa",
    "name": "Ibtv USA",
    "category": "International",
    "logo": "https://s3.aynaott.com/storage/1678abdbf203bb77af4bbf2905a3de59",
    "servers": [
      {
        "url": "https://tvsen7.aynascope.net/ibtvusa/index.m3u8?e=1773791021&u=78be6644-0a65-48ec-81a4-089ac65a2619&token=e7b321a793791f7757f9dee54db819d2",
        "latency": 1715,
        "quality": "",
        "stability": 1,
        "type": "hls"
      }
    ]
  },
  {
    "id": "iraninternational",
    "name": "Iran International",
    "category": "International",
    "logo": "",
    "servers": [
      {
        "url": "https://dev-live.livetvstream.co.uk/LS-63503-4/chunklist_b1196000.m3u8",
        "latency": 193,
        "quality": "",
        "stability": 1,
        "type": "hls"
      }
    ]
  },
  {
    "id": "manatvinternational",
    "name": "Mana Tv International",
    "category": "International",
    "logo": "https://d229kpbsb5jevy.cloudfront.net/yuppfast/content/common/channel/logos/mana-tv-international.png",
    "epg_id": "216",
    "servers": [
      {
        "url": "https://livegeorouus.akamaized.net/090823/smil:manatvint.smil/playlist.m3u8?hdnts=st%3D1773782482~exp%3D1773804082~acl%3D%21%2A%2F090823%2Fsmil%3Amanatvint.smil%2F%2A%21%2Fpayload%2Fyupptvott_5_-1_7c03c72952b44aa4_DE_135.232.185.19_yuppfast_2_channel_216_-1%2F%2A~data%3Dyupptvott_5_-1_7c03c72952b44aa4_DE_135.232.185.19_yuppfast_2_channel_216_-1~hmac%3D52e811a0b1a40c5b45dcfc4d10fb15439667123c4f87aa4274b5c9fb85e28e73",
        "latency": 65,
        "quality": "HD",
        "stability": 1,
        "type": "hls"
      }
    ]
  },
  {
    "id": "ntvuk",
    "name": "NTV Uk",
    "category": "International",
    "logo": "",
    "servers": [
      {
        "url": "https://app.ncare.live/c3VydmVyX8RpbEU9Mi8xNy8yMDE0GIDU6RgzQ6NTAgdEoaeFzbF92YWxIZTO0U0ezN1IzMyfvcGVMZEJCTEFWeVN3PTOmdFsaWRtaW51aiPhnPTI2/ntvuk00332211.stream/playlist.m3u8",
        "latency": 166,
        "quality": "",
        "stability": 1,
        "type": "hls"
      }
    ]
  },
  {
    "id": "thechukkerchannel",
    "name": "The Chukker Channel",
    "category": "International",
    "logo": "https://d229kpbsb5jevy.cloudfront.net/yuppfast/content/common/channel/logos/rrkxqp.png",
    "epg_id": "67",
    "servers": [
      {
        "url": "https://streams2.sofast.tv/ptnr-YuppTV/title-THE-CHUKKER-CHANNEL-INT_yupptv/v1/master/611d79b11b77e2f571934fd80ca1413453772ac7/3bd726a3-0d30-491d-b5e7-e1afb6e02112/master.m3u8?hdnts=st%3D1773782527~exp%3D1773804127~acl%3D%21%2A%2Fptnr-YuppTV%2Ftitle-THE-CHUKKER-CHANNEL-INT_yupptv%2Fv1%2Fmaster%2F611d79b11b77e2f571934fd80ca1413453772ac7%2F3bd726a3-0d30-491d-b5e7-e1afb6e02112%2F%2A%21%2Fpayload%2Fyupptvott_5_-1_7c03c72952b44aa4_DE_135.232.185.19_yuppfast_2_channel_67_-1%2F%2A~data%3Dyupptvott_5_-1_7c03c72952b44aa4_DE_135.232.185.19_yuppfast_2_channel_67_-1~hmac%3D990e054a5b48a10a27a73ba3a186449131e9c72dc8c6d39dfd0541ff9fbf1424",
        "latency": 472,
        "quality": "HD",
        "stability": 1,
        "type": "hls"
      }
    ]
  },
  {
    "id": "timetvusa",
    "name": "Time Tv USA",
    "category": "International",
    "logo": "https://s3.aynaott.com/storage/111bfd01fb43770e925ca9cf16663f56",
    "servers": [
      {
        "url": "https://tvsen7.aynascope.net/timetv/index.m3u8?e=1773790854&u=78be6644-0a65-48ec-81a4-089ac65a2619&token=d14c36904cf00641991522285d4216d7",
        "latency": 1580,
        "quality": "",
        "stability": 1,
        "type": "hls"
      }
    ]
  },
  {
    "id": "usatv",
    "name": "USA Tv",
    "category": "International",
    "logo": "https://s3.aynaott.com/storage/376b8483457b06dbc5b7b7b327a21ac6",
    "servers": [
      {
        "url": "https://tvsen6.aynascope.net/usa/index.m3u8?e=1773791026&u=78be6644-0a65-48ec-81a4-089ac65a2619&token=1d472d2b9f6d16968925e471e8491f47",
        "latency": 919,
        "quality": "",
        "stability": 1,
        "type": "hls"
      }
    ]
  },
  {
    "id": "zeebanglainternational",
    "name": "ZEE Bangla International",
    "category": "International",
    "logo": "https://s3.aynaott.com/storage/0cb865748deefd42e69fd9a221cf38ee",
    "servers": [
      {
        "url": "https://tvsen5.aynascope.net/PNEb3v2q6GBk/index.m3u8?e=1773791070&u=78be6644-0a65-48ec-81a4-089ac65a2619&token=ae6521f5cf99400c4253ea9ef54b5949",
        "latency": 1232,
        "quality": "",
        "stability": 1,
        "type": "hls"
      }
    ]
  },
  {
    "id": "zeeupuk",
    "name": "ZEE Up Uk",
    "category": "International",
    "logo": "https://d229kpbsb5jevy.cloudfront.net/yuppfast/content/common/channel/logos/ipyfdr.png",
    "epg_id": "29",
    "servers": [
      {
        "url": "https://vg-zeefta.akamaized.net/ptnr-yupptv/title-zeeupuk/v1/master/611d79b11b77e2f571934fd80ca1413453772ac7/a8c57b70-538f-49ae-af12-2fc2acaa4ff1/main.m3u8?hdnts=st%3D1773782437~exp%3D1773804037~acl%3D%21%2A%2Fptnr-yupptv%2Ftitle-zeeupuk%2Fv1%2Fmaster%2F611d79b11b77e2f571934fd80ca1413453772ac7%2Fa8c57b70-538f-49ae-af12-2fc2acaa4ff1%2F%2A%21%2Fpayload%2Fyupptvott_5_-1_7c03c72952b44aa4_DE_135.232.185.19_yuppfast_2_channel_29_-1%2F%2A~data%3Dyupptvott_5_-1_7c03c72952b44aa4_DE_135.232.185.19_yuppfast_2_channel_29_-1~hmac%3D1bc2e7f8fb01cb5c4923b631b0b2a8a63eb921f41db2501429c9f69cc67299e4",
        "latency": 645,
        "quality": "HD",
        "stability": 1,
        "type": "hls"
      }
    ]
  }
]
