[
  {
    "id": "andtv",
    "name": "& TV",
    "category": "Movies",
    "logo": "https://xstreamcp-assets-msp.streamready.in/assets/LIVETV/LIVECHANNEL/LIVETV_LIVETVCHANNEL_SYMANDTV/images/LOGO_HD/LOGO_HD_image.png",
    "epg_id": "AndTV.in@SD",
    "servers": [
      {
        "url": "http://103.229.254.25:7001/play/a09v/index.m3u8",
        "latency": 554,
        "quality": "",
        "stability": 0.9878542510121457,
        "type": "hls"
      },
      {
        "url": "http://103.229.254.25:7001/play/a034/index.m3u8",
        "latency": 556,
        "quality": "FHD",
        "stability": 0.9635627530364372,
        "type": "hls"
      }
    ]
  },
  {
    "id": "andflix",
    "name": "&flix",
    "category": "Movies",
    "logo": "https://xstreamcp-assets-msp.streamready.in/assets/LIVETV/LIVECHANNEL/LIVETV_LIVETVCHANNEL_SYMANDFLIX/images/LOGO_HD/LOGO_HD_image.png",
    "epg_id": "Andflix.in@HD",
    "servers": [
      {
        "url": "http://116.90.120.151:8000/play/a0il/index.m3u8",
        "latency": 518,
        "quality": "FHD",
        "stability": 1,
        "type": "hls"
      }
    ]
  },
  {
    "id": "andprive",
    "name": "&prive",
    "category": "Movies",
    "logo": "https://dtil.tmsimg.com/assets/GNLZZGG0022J69M.png?lock=720x540",
    "epg_id": "AndpriveHD.in@SD",
    "servers": [
      {
        "url": "http://116.90.120.151:8000/play/a0it/index.m3u8",
        "latency": 520,
        "quality": "FHD",
        "stability": 1,
        "type": "hls"
      }
    ]
  },
  {
    "id": "actionhollywoodmovies",
    "name": "Action Hollywood Movies",
    "category": "Movies",
    "logo": "https://s3.aynaott.com/storage/baef6dd41c3ee6fabbb59bb8403cc1eb",
    "servers": [
      {
        "url": "https://amg01076-lightningintern-actionhollywood-samsungnz-82rry.amagi.tv/playlist/amg01076-lightningintern-actionhollywood-samsungnz/playlist.m3u8",
        "latency": 138,
        "quality": "",
        "stability": 1,
        "type": "hls"
      },
      {
        "url": "https://cdn-apse1-prod.tsv2.amagi.tv/linear/amg01076-lightningintern-actionhollywood-samsungnz/playlist.m3u8",
        "latency": 889,
        "quality": "",
        "stability": 1,
        "type": "hls"
      }
    ]
  },
  {
    "id": "alankartv",
    "name": "Alankar Tv",
    "category": "Movies",
    "logo": "https://xstreamcp-assets-msp.streamready.in/assets/LIVETV/LIVECHANNEL/LIVETV_LIVETVCHANNEL_ALANKAR/images/LOGO_HD/image.png",
    "epg_id": "AlankarTV.in@SD",
    "servers": [
      {
        "url": "https://livetv.tarangplus.in/alankar-origin/live/playlist.m3u8",
        "latency": 523,
        "quality": "HD",
        "stability": 0.9919028340080972,
        "type": "hls"
      }
    ]
  },
  {
    "id": "alltimemovies",
    "name": "All Time Movies",
    "category": "Movies",
    "logo": "https://yt3.googleusercontent.com/U4INXhwmEUOABHoemQBpI6C9t4jb9iBmDvZ3ZT3lAb9Au_jVl32NL8XDpy-9cBjRJ2LP69Ovzg=s900-c-k-c0x00ffffff-no-rj",
    "epg_id": "AllTimeMovies.in@SD",
    "servers": [
      {
        "url": "https://mumt03.tangotv.in/ALLTIMEMOVIES/index.m3u8",
        "latency": 1160,
        "quality": "",
        "stability": 0.9959514170040485,
        "type": "hls"
      }
    ]
  },
  {
    "id": "anmolcinema",
    "name": "Anmol Cinema",
    "category": "Movies",
    "logo": "https://dtil.tmsimg.com/assets/GNLZZGG00260YG8.png?lock=720x540",
    "epg_id": "AnmolCinema.in@SD",
    "servers": [
      {
        "url": "http://116.90.120.151:8000/play/a0j6/index.m3u8",
        "latency": 513,
        "quality": "",
        "stability": 0.9806451612903225,
        "type": "hls"
      }
    ]
  },
  {
    "id": "b4ubhojpuri",
    "name": "B4U Bhojpuri",
    "category": "Movies",
    "logo": "https://i.imgur.com/NwOQUDp.png",
    "epg_id": "B4UBhojpuri.in@SD",
    "servers": [
      {
        "url": "https://cdnb4u.wiseplayout.com/B4U_Bhojpuri/master.m3u8",
        "latency": 143,
        "quality": "FHD",
        "stability": 0.9757085020242915,
        "type": "hls"
      }
    ]
  },
  {
    "id": "b4umoviesindia",
    "name": "B4U Movies India",
    "category": "Movies",
    "logo": "https://s3.aynaott.com/storage/5088d0894a79b329031d5f4669bbb0fe",
    "servers": [
      {
        "url": "https://cdnb4u.wiseplayout.com/B4U_Movies/master.m3u8",
        "latency": 292,
        "quality": "",
        "stability": 0.9601593625498008,
        "type": "hls"
      }
    ]
  },
  {
    "id": "bestactiontv",
    "name": "Best Action Tv",
    "category": "Movies",
    "logo": "https://d229kpbsb5jevy.cloudfront.net/yuppfast/content/common/channel/logos/fjbfto.png",
    "epg_id": "256",
    "servers": [
      {
        "url": "https://streams2.sofast.tv/v1/master/611d79b11b77e2f571934fd80ca1413453772ac7/12a9fc64-24ca-491e-b86c-be18c9be047b/manifest.m3u8?hdnts=st%3D1774595537~exp%3D1774617137~acl%3D%21%2A%2Fv1%2Fmaster%2F611d79b11b77e2f571934fd80ca1413453772ac7%2F12a9fc64-24ca-491e-b86c-be18c9be047b%2F%2A%21%2Fpayload%2Fyupptvott_5_-1_7c03c72952b44aa4_DE_64.236.201.34_yuppfast_2_channel_256_-1%2F%2A~data%3Dyupptvott_5_-1_7c03c72952b44aa4_DE_64.236.201.34_yuppfast_2_channel_256_-1~hmac%3D7ab2295c70cf8a9224524bbc2623676aecdbef17854b33ac58b267b133de91a6",
        "latency": 412,
        "quality": "HD",
        "stability": 1,
        "type": "hls"
      }
    ]
  },
  {
    "id": "bestdramatv",
    "name": "Best Drama Tv",
    "category": "Movies",
    "logo": "https://d229kpbsb5jevy.cloudfront.net/yuppfast/content/common/channel/logos/vuyumm.png",
    "epg_id": "257",
    "servers": [
      {
        "url": "https://streams2.sofast.tv/ptnr-yupptv/title-BEST_DRAMA_YUPPTV/v1/master/611d79b11b77e2f571934fd80ca1413453772ac7/9800ea5c-2183-4160-9f01-70e5d6428a50/manifest.m3u8?hdnts=st%3D1774595538~exp%3D1774617138~acl%3D%21%2A%2Fptnr-yupptv%2Ftitle-BEST_DRAMA_YUPPTV%2Fv1%2Fmaster%2F611d79b11b77e2f571934fd80ca1413453772ac7%2F9800ea5c-2183-4160-9f01-70e5d6428a50%2F%2A%21%2Fpayload%2Fyupptvott_5_-1_7c03c72952b44aa4_DE_64.236.201.34_yuppfast_2_channel_257_-1%2F%2A~data%3Dyupptvott_5_-1_7c03c72952b44aa4_DE_64.236.201.34_yuppfast_2_channel_257_-1~hmac%3D456ca571b1fbafabc465bd3f2c968417d218756edf2141467e7d66685bc6df20",
        "latency": 170,
        "quality": "HD",
        "stability": 1,
        "type": "hls"
      }
    ]
  },
  {
    "id": "bestthrillertv",
    "name": "Best Thriller Tv",
    "category": "Movies",
    "logo": "https://d229kpbsb5jevy.cloudfront.net/yuppfast/content/common/channel/logos/ewehpt.png",
    "epg_id": "258",
    "servers": [
      {
        "url": "https://streams2.sofast.tv/ptnr-yupptv/title-BEST_THRILLER_YUPPTV/v1/master/611d79b11b77e2f571934fd80ca1413453772ac7/ce168a85-c8d4-41d6-a597-cc8fd7baddd9/manifest.m3u8?hdnts=st%3D1774595538~exp%3D1774617138~acl%3D%21%2A%2Fptnr-yupptv%2Ftitle-BEST_THRILLER_YUPPTV%2Fv1%2Fmaster%2F611d79b11b77e2f571934fd80ca1413453772ac7%2Fce168a85-c8d4-41d6-a597-cc8fd7baddd9%2F%2A%21%2Fpayload%2Fyupptvott_5_-1_7c03c72952b44aa4_DE_64.236.201.34_yuppfast_2_channel_258_-1%2F%2A~data%3Dyupptvott_5_-1_7c03c72952b44aa4_DE_64.236.201.34_yuppfast_2_channel_258_-1~hmac%3D22ce19d7ae94cf6aea976ed060aded858a2c8d8c6a97ad49434be49c537c3deb",
        "latency": 676,
        "quality": "HD",
        "stability": 1,
        "type": "hls"
      }
    ]
  },
  {
    "id": "bhojpuricinema",
    "name": "Bhojpuri Cinema",
    "category": "Movies",
    "logo": "https://xstreamcp-assets-msp.streamready.in/assets/LIVETV/LIVECHANNEL/LIVETV_LIVETVCHANNEL_BHOJPURI_CINEMA/images/LOGO_HD/image.png",
    "epg_id": "BhojpuriCinema.in@SD",
    "servers": [
      {
        "url": "https://live-bhojpuri.akamaized.net/liveabr/playlist.m3u8",
        "latency": 688,
        "quality": "HD",
        "stability": 1,
        "type": "hls"
      }
    ]
  },
  {
    "id": "bollywoodmovies",
    "name": "Bollywood Movies",
    "category": "Movies",
    "logo": "",
    "servers": [
      {
        "url": "https://cloudfrontnet.vercel.app/tplay/playout/209612/master.m3u8",
        "latency": 122,
        "quality": "",
        "stability": 0.9836734693877551,
        "type": "hls"
      },
      {
        "url": "https://cloudfrontnet.vercel.app/tplay/playout/209593/master.m3u8",
        "latency": 265,
        "quality": "",
        "stability": 0.9714285714285714,
        "type": "hls"
      }
    ]
  },
  {
    "id": "colorsbanglacinema",
    "name": "Colors Bangla Cinema",
    "category": "Movies",
    "logo": "https://xstreamcp-assets-msp.streamready.in/assets/LIVETV/LIVECHANNEL/LIVETV_LIVETVCHANNEL_COLORS_BANGLA_CINEMA/images/LOGO_HD/image.png",
    "epg_id": "ColorsBanglaCinema.in@SD",
    "servers": [
      {
        "url": "http://116.90.120.151:8000/play/a0jh/index.m3u8",
        "latency": 524,
        "quality": "",
        "stability": 0.967741935483871,
        "type": "hls"
      }
    ]
  },
  {
    "id": "colorscineplex",
    "name": "Colors Cineplex",
    "category": "Movies",
    "logo": "https://xstreamcp-assets-msp.streamready.in/assets/LIVETV/LIVECHANNEL/LIVETV_LIVETVCHANNEL_COLORS_CINEPLEX_HD/images/LOGO_HD/image.png",
    "epg_id": "ColorsCineplex.in@HD",
    "servers": [
      {
        "url": "http://116.90.120.151:8000/play/a0ji/index.m3u8",
        "latency": 516,
        "quality": "FHD",
        "stability": 1,
        "type": "hls"
      }
    ]
  },
  {
    "id": "colorscineplexsuperhits",
    "name": "Colors Cineplex Superhits",
    "category": "Movies",
    "logo": "https://xstreamcp-assets-msp.streamready.in/assets/LIVETV/LIVECHANNEL/LIVETV_LIVETVCHANNEL_COLORS_CINEPLEX_SUPERHITS/images/LOGO_HD/image.png",
    "epg_id": "ColorsCineplexSuperhits.in@SD",
    "servers": [
      {
        "url": "http://116.90.120.151:8000/play/a0kl/index.m3u8",
        "latency": 525,
        "quality": "",
        "stability": 1,
        "type": "hls"
      }
    ]
  },
  {
    "id": "cowboymoviechannel",
    "name": "Cowboy Movie Channel",
    "category": "Movies",
    "logo": "https://d229kpbsb5jevy.cloudfront.net/yuppfast/content/common/channel/logos/cowboy-movie-channel.png",
    "epg_id": "52",
    "servers": [
      {
        "url": "https://streams2.sofast.tv/ptnr-yupptv/title-COWBOY-MOVIE-CHANNEL-ENG_yupptv/v1/master/611d79b11b77e2f571934fd80ca1413453772ac7/4434fd47-6d46-43e9-b132-fab122edc732/manifest.m3u8?hdnts=st%3D1774595534~exp%3D1774617134~acl%3D%21%2A%2Fptnr-yupptv%2Ftitle-COWBOY-MOVIE-CHANNEL-ENG_yupptv%2Fv1%2Fmaster%2F611d79b11b77e2f571934fd80ca1413453772ac7%2F4434fd47-6d46-43e9-b132-fab122edc732%2F%2A%21%2Fpayload%2Fyupptvott_5_-1_7c03c72952b44aa4_DE_64.236.201.34_yuppfast_2_channel_52_-1%2F%2A~data%3Dyupptvott_5_-1_7c03c72952b44aa4_DE_64.236.201.34_yuppfast_2_channel_52_-1~hmac%3D3a49e2afb36df7a23c0da580c741760daf711da5cf67ca655f606eaf7648bd14",
        "latency": 917,
        "quality": "HD",
        "stability": 1,
        "type": "hls"
      }
    ]
  },
  {
    "id": "dhamakamovies",
    "name": "Dhamaka Movies",
    "category": "Movies",
    "logo": "https://s3.aynaott.com/storage/d63eff8864579b144c097c549ec0470a",
    "servers": [
      {
        "url": "https://tvsen7.aynascope.net/DhamakaMovies/index.m3u8?e=1774601330&u=78be6644-0a65-48ec-81a4-089ac65a2619&token=0cea4387b8d059d2823dbf0be64d925c",
        "latency": 940,
        "quality": "",
        "stability": 1,
        "type": "hls"
      }
    ]
  },
  {
    "id": "dhamakamoviesb4u",
    "name": "Dhamaka Movies B4U",
    "category": "Movies",
    "logo": "https://www.lyngsat.com/logo/tv/dd/dhamaka-movies-b4u-in.png",
    "epg_id": "DhamakaMoviesB4U.in@SD",
    "servers": [
      {
        "url": "https://cdn-1.pishow.tv/live/235/master.m3u8",
        "latency": 566,
        "quality": "",
        "stability": 0.9878542510121457,
        "type": "hls"
      }
    ]
  },
  {
    "id": "driveinmoviechannel",
    "name": "Drive In Movie Channel",
    "category": "Movies",
    "logo": "https://d229kpbsb5jevy.cloudfront.net/yuppfast/content/common/channel/logos/drive-in-movie-channel.png",
    "epg_id": "55",
    "servers": [
      {
        "url": "https://streams2.sofast.tv/ptnr-yupptv/title-DRIVE-IN-MOVIE-CHANNEL-ENG_yupptv/v1/master/611d79b11b77e2f571934fd80ca1413453772ac7/e5056383-20ac-488f-b299-6577f66881ff/manifest.m3u8?hdnts=st%3D1774595536~exp%3D1774617136~acl%3D%21%2A%2Fptnr-yupptv%2Ftitle-DRIVE-IN-MOVIE-CHANNEL-ENG_yupptv%2Fv1%2Fmaster%2F611d79b11b77e2f571934fd80ca1413453772ac7%2Fe5056383-20ac-488f-b299-6577f66881ff%2F%2A%21%2Fpayload%2Fyupptvott_5_-1_7c03c72952b44aa4_DE_64.236.201.34_yuppfast_2_channel_55_-1%2F%2A~data%3Dyupptvott_5_-1_7c03c72952b44aa4_DE_64.236.201.34_yuppfast_2_channel_55_-1~hmac%3Ddcb98d5243602ba8b152d150e7213559a84cc5dc4e6ec9cef72c523eb0e8c5ca",
        "latency": 1064,
        "quality": "HD",
        "stability": 1,
        "type": "hls"
      }
    ]
  },
  {
    "id": "filamchibhojpuri",
    "name": "Filamchi Bhojpuri",
    "category": "Movies",
    "logo": "https://dtil.tmsimg.com/assets/s157803_ld_h15_aa.png?lock=720x540",
    "epg_id": "FilamchiBhojpuri.in@SD",
    "servers": [
      {
        "url": "https://epiconvh.akamaized.net/live/filamchi/master.m3u8",
        "latency": 497,
        "quality": "FHD",
        "stability": 1,
        "type": "hls"
      }
    ]
  },
  {
    "id": "gserise",
    "name": "G Serise",
    "category": "Movies",
    "logo": "",
    "servers": [
      {
        "url": "https://vods2.aynaott.com/gseriesDrama/tracks-v1a1/mono.ts.m3u8",
        "latency": 264,
        "quality": "SD",
        "stability": 0.950207468879668,
        "type": "hls"
      }
    ]
  },
  {
    "id": "goldmines",
    "name": "Goldmines",
    "category": "Movies",
    "logo": "https://xstreamcp-assets-msp.streamready.in/assets/LIVETV/LIVECHANNEL/LIVETV_LIVETVCHANNEL_GOLDMINES/images/LOGO_HD/image.png",
    "epg_id": "Goldmines.in@SD",
    "servers": [
      {
        "url": "https://cdn-2.pishow.tv/live/1459/master.m3u8",
        "latency": 636,
        "quality": "",
        "stability": 0.9959839357429718,
        "type": "hls"
      }
    ]
  },
  {
    "id": "goldmines2",
    "name": "Goldmines 2",
    "category": "Movies",
    "logo": "https://www.lyngsat.com/logo/tv/gg/goldmines-2-in.png",
    "epg_id": "Goldmines2.in@SD",
    "servers": [
      {
        "url": "https://cdn-2.pishow.tv/live/1460/master.m3u8",
        "latency": 783,
        "quality": "",
        "stability": 1,
        "type": "hls"
      }
    ]
  },
  {
    "id": "goldminesbollywood",
    "name": "Goldmines Bollywood",
    "category": "Movies",
    "logo": "",
    "servers": [
      {
        "url": "http://103.175.73.12:8080/live/52/52_0.m3u8",
        "latency": 854,
        "quality": "",
        "stability": 1,
        "type": "hls"
      }
    ]
  },
  {
    "id": "goldminesmovies",
    "name": "Goldmines Movies",
    "category": "Movies",
    "logo": "https://s3.aynaott.com/storage/f8d9220406fa9ae79006914639f52e9b",
    "epg_id": "GoldminesMovies.in@SD",
    "servers": [
      {
        "url": "https://tvsen6.aynascope.net/GoldminesMovies/index.m3u8?e=1774601313&u=78be6644-0a65-48ec-81a4-089ac65a2619&token=e32812b863fcd5fc438819b550fba8fb",
        "latency": 657,
        "quality": "",
        "stability": 1,
        "type": "hls"
      },
      {
        "url": "https://cdn-2.pishow.tv/live/1461/master.m3u8",
        "latency": 797,
        "quality": "",
        "stability": 1,
        "type": "hls"
      }
    ]
  },
  {
    "id": "hbo",
    "name": "HBO",
    "category": "Movies",
    "logo": "https://s3.aynaott.com/storage/4a1291716680b5c095d33e106337bb04",
    "servers": [
      {
        "url": "https://tvsen5.aynascope.net/hbo/index.m3u8?e=1774601284&u=78be6644-0a65-48ec-81a4-089ac65a2619&token=677869662ff03ac9c059404aa2c8f611",
        "latency": 767,
        "quality": "",
        "stability": 1,
        "type": "hls"
      }
    ]
  },
  {
    "id": "hbo2",
    "name": "HBO 2",
    "category": "Movies",
    "logo": "https://s3.aynaott.com/storage/b64c028d8c0895ed81f3201d5979f7ba",
    "servers": [
      {
        "url": "https://tvsen7.aynascope.net/hbo2/index.m3u8?e=1774601293&u=78be6644-0a65-48ec-81a4-089ac65a2619&token=9fee121ab438cb9d0076e6f98a5d375c",
        "latency": 931,
        "quality": "",
        "stability": 1,
        "type": "hls"
      }
    ]
  },
  {
    "id": "hindimovieclassic24",
    "name": "Hindi Movie Classic 24",
    "category": "Movies",
    "logo": "https://s3.aynaott.com/storage/3132515182ec50091b496fe515564084",
    "servers": [
      {
        "url": "https://vods2.aynaott.com/hindimovies/index.m3u8",
        "latency": 804,
        "quality": "",
        "stability": 1,
        "type": "hls"
      }
    ]
  },
  {
    "id": "hindimovies",
    "name": "Hindi Movies",
    "category": "Movies",
    "logo": "",
    "servers": [
      {
        "url": "https://live20.bozztv.com/giatvplayout7/giatv-209612/tracks-v1a1/mono.ts.m3u8",
        "latency": 38,
        "quality": "",
        "stability": 0.934156378600823,
        "type": "hls"
      }
    ]
  },
  {
    "id": "horrortv",
    "name": "Horror Tv",
    "category": "Movies",
    "logo": "https://d229kpbsb5jevy.cloudfront.net/yuppfast/content/common/channel/logos/horror-tv.png",
    "epg_id": "77",
    "servers": [
      {
        "url": "https://streams2.sofast.tv/ptnr-yupptv/title-HORROR-TV-ENG_yupptv/v1/master/611d79b11b77e2f571934fd80ca1413453772ac7/93dc292b-cbcf-4988-ab97-94feced4c14b/master.m3u8?hdnts=st%3D1774595536~exp%3D1774617136~acl%3D%21%2A%2Fptnr-yupptv%2Ftitle-HORROR-TV-ENG_yupptv%2Fv1%2Fmaster%2F611d79b11b77e2f571934fd80ca1413453772ac7%2F93dc292b-cbcf-4988-ab97-94feced4c14b%2F%2A%21%2Fpayload%2Fyupptvott_5_-1_7c03c72952b44aa4_DE_64.236.201.34_yuppfast_2_channel_77_-1%2F%2A~data%3Dyupptvott_5_-1_7c03c72952b44aa4_DE_64.236.201.34_yuppfast_2_channel_77_-1~hmac%3Da42a4fc8e8923cfbd957f06dc89f6c63ed287977c40d99d6fe18d5e45e691416",
        "latency": 346,
        "quality": "HD",
        "stability": 1,
        "type": "hls"
      }
    ]
  },
  {
    "id": "indywoodtv",
    "name": "Indywood Tv",
    "category": "Movies",
    "logo": "https://i.ibb.co/jT3NCPp/logo-tv.png",
    "epg_id": "IndywoodTV.in@SD",
    "servers": [
      {
        "url": "https://43wrzjnpqoxe-hls-live.wmncdn.net/indywood/indywoodtv/index.m3u8",
        "latency": 656,
        "quality": "HD",
        "stability": 1,
        "type": "hls"
      }
    ]
  },
  {
    "id": "jalshamovies",
    "name": "Jalsha Movies",
    "category": "Movies",
    "logo": "https://i.imgur.com/25eWjX2.png",
    "epg_id": "JalshaMovies.in@HD",
    "servers": [
      {
        "url": "http://103.229.254.25:7001/play/a0dt/index.m3u8",
        "latency": 535,
        "quality": "FHD",
        "stability": 0.9799196787148594,
        "type": "hls"
      }
    ]
  },
  {
    "id": "kairaliwe",
    "name": "Kairali We",
    "category": "Movies",
    "logo": "https://xstreamcp-assets-msp.streamready.in/assets/LIVETV/LIVECHANNEL/LIVETV_LIVETVCHANNEL_KAIRALI_WE/images/LOGO_HD/image.png",
    "epg_id": "KairaliWe.in@SD",
    "servers": [
      {
        "url": "https://cdn-3.pishow.tv/live/1530/master.m3u8",
        "latency": 715,
        "quality": "",
        "stability": 1,
        "type": "hls"
      }
    ]
  },
  {
    "id": "khushboo",
    "name": "Khushboo",
    "category": "Movies",
    "logo": "https://s3.aynaott.com/storage/d90eb718a6674494d2dac28e1d96bf44",
    "servers": [
      {
        "url": "https://cdn-4.pishow.tv/live/1473/master.m3u8",
        "latency": 672,
        "quality": "",
        "stability": 0.9960159362549801,
        "type": "hls"
      }
    ]
  },
  {
    "id": "kolkatamovies",
    "name": "Kolkata Movies",
    "category": "Movies",
    "logo": "",
    "servers": [
      {
        "url": "https://cloudfrontnet.vercel.app/tplay/playout/209627/master.m3u8",
        "latency": 115,
        "quality": "",
        "stability": 0.9836734693877551,
        "type": "hls"
      }
    ]
  },
  {
    "id": "kungfu",
    "name": "Kung Fu",
    "category": "Movies",
    "logo": "https://d229kpbsb5jevy.cloudfront.net/yuppfast/content/common/channel/logos/kung-fu.png",
    "epg_id": "85",
    "servers": [
      {
        "url": "https://streams2.sofast.tv/ptnr-yupptv/title-KUNG-FU-ENG_yupptv/v1/master/611d79b11b77e2f571934fd80ca1413453772ac7/06862a07-6a92-4b4d-abc3-5fea131713b5/manifest.m3u8?hdnts=st%3D1774595537~exp%3D1774617137~acl%3D%21%2A%2Fptnr-yupptv%2Ftitle-KUNG-FU-ENG_yupptv%2Fv1%2Fmaster%2F611d79b11b77e2f571934fd80ca1413453772ac7%2F06862a07-6a92-4b4d-abc3-5fea131713b5%2F%2A%21%2Fpayload%2Fyupptvott_5_-1_7c03c72952b44aa4_DE_64.236.201.34_yuppfast_2_channel_85_-1%2F%2A~data%3Dyupptvott_5_-1_7c03c72952b44aa4_DE_64.236.201.34_yuppfast_2_channel_85_-1~hmac%3Dbb62ad278ea76a79afd5d98985680ef364a7a1ea6b0b8087797fea33862c649d",
        "latency": 357,
        "quality": "HD",
        "stability": 1,
        "type": "hls"
      }
    ]
  },
  {
    "id": "mahamovie",
    "name": "Maha Movie",
    "category": "Movies",
    "logo": "https://jiotvimages.cdn.jio.com/dare_images/images/Maha_Movies.png",
    "epg_id": "MahaMovie.in@SD",
    "servers": [
      {
        "url": "https://cdn-6.pishow.tv/live/10007/master.m3u8",
        "latency": 653,
        "quality": "",
        "stability": 1,
        "type": "hls"
      }
    ]
  },
  {
    "id": "manoranjangrand",
    "name": "Manoranjan Grand",
    "category": "Movies",
    "logo": "https://dtil.tmsimg.com/assets/s143302_ld_h15_aa.png?lock=720x540",
    "epg_id": "ManoranjanGrand.in@SD",
    "servers": [
      {
        "url": "https://cdn-1.pishow.tv/live/1011/master.m3u8",
        "latency": 247,
        "quality": "HD",
        "stability": 0.9959514170040485,
        "type": "hls"
      }
    ]
  },
  {
    "id": "maxmovies",
    "name": "Max Movies",
    "category": "Movies",
    "logo": "https://livetv.ashokadigital.net/upload/logo/1732168422_WhatsApp%20Image%202024-11-21%20at%2010.18.47%20AM.jpeg",
    "epg_id": "MaxMovies.in@HD",
    "servers": [
      {
        "url": "https://live.maxtn.in/maxmovies/maxmovies/index.m3u8",
        "latency": 854,
        "quality": "FHD",
        "stability": 0.9919028340080972,
        "type": "hls"
      }
    ]
  },
  {
    "id": "mhonemovies",
    "name": "Mh One Movies",
    "category": "Movies",
    "logo": "https://www.lyngsat.com/logo/tv/mm/mh-1-movies-in.png",
    "epg_id": "MHOneMovies.in@SD",
    "servers": [
      {
        "url": "https://mumt03.tangotv.in/MHONEMOVIE/index.m3u8",
        "latency": 843,
        "quality": "",
        "stability": 0.8097165991902834,
        "type": "hls"
      }
    ]
  },
  {
    "id": "moviebangla",
    "name": "Movie Bangla",
    "category": "Movies",
    "logo": "https://s3.aynaott.com/storage/a535fd3aae1f5dc79e9afa561cf28983",
    "epg_id": "MovieBangla.bd@SD",
    "servers": [
      {
        "url": "https://tvsen7.aynascope.net/moviebangla/index.m3u8?e=1774601255&u=78be6644-0a65-48ec-81a4-089ac65a2619&token=12c21a6be05d76f7ebd07f96211a50d5",
        "latency": 675,
        "quality": "",
        "stability": 1,
        "type": "hls"
      },
      {
        "url": "http://alvetv.com/moviebanglatv/8080/index.m3u8",
        "latency": 2084,
        "quality": "",
        "stability": 0.8904109589041096,
        "type": "hls"
      }
    ]
  },
  {
    "id": "movieplex",
    "name": "Movieplex",
    "category": "Movies",
    "logo": "https://i.imgur.com/THJEAqJ.png",
    "epg_id": "MoviePlex.in@SD",
    "servers": [
      {
        "url": "https://mumt04.tangotv.in/MOVIEPLEX/index.m3u8",
        "latency": 375,
        "quality": "",
        "stability": 0.9959514170040485,
        "type": "hls"
      }
    ]
  },
  {
    "id": "moviesnow",
    "name": "Movies Now",
    "category": "Movies",
    "logo": "https://xstreamcp-assets-msp.streamready.in/assets/LIVETV/LIVECHANNEL/LIVETV_LIVETVCHANNEL_MOVIES_NOW/images/LOGO_HD/image.png",
    "epg_id": "MoviesNow.in@HD",
    "servers": [
      {
        "url": "http://116.90.120.151:8000/play/a0ib/index.m3u8",
        "latency": 514,
        "quality": "FHD",
        "stability": 1,
        "type": "hls"
      },
      {
        "url": "http://116.90.120.151:8000/play/a0i4/index.m3u8",
        "latency": 532,
        "quality": "FHD",
        "stability": 1,
        "type": "hls"
      }
    ]
  },
  {
    "id": "moviesphere",
    "name": "Moviesphere",
    "category": "Movies",
    "logo": "https://s3.aynaott.com/storage/4d343b446b1e7164bb7239bbe822a570",
    "servers": [
      {
        "url": "https://moviesphereuk-samsunguk.amagi.tv/playlist.m3u8",
        "latency": 233,
        "quality": "",
        "stability": 1,
        "type": "hls"
      }
    ]
  },
  {
    "id": "oscarmoviesbhojpuri",
    "name": "Oscar Movies Bhojpuri",
    "category": "Movies",
    "logo": "https://dtil.tmsimg.com/assets/s143638_ld_h9_ab.png?lock=720x540",
    "epg_id": "OscarMoviesBhojpuri.in@SD",
    "servers": [
      {
        "url": "https://cdn-4.pishow.tv/live/233/master.m3u8",
        "latency": 788,
        "quality": "HD",
        "stability": 1,
        "type": "hls"
      }
    ]
  },
  {
    "id": "osnmoviesaction",
    "name": "Osn Movies Action",
    "category": "Movies",
    "logo": "https://i.imgur.com/uOzyKup.png",
    "epg_id": "OSNMoviesAction.ae@SD",
    "servers": [
      {
        "url": "http://116.90.120.151:8000/play/a0ax/index.m3u8",
        "latency": 523,
        "quality": "FHD",
        "stability": 0.8732394366197183,
        "type": "hls"
      }
    ]
  },
  {
    "id": "persianakore",
    "name": "Persiana Kore",
    "category": "Movies",
    "logo": "https://s3.aynaott.com/storage/f24e50516ccf6b3e94a4ca749ccb3533",
    "servers": [
      {
        "url": "https://korhls.persiana.live/hls/stream.m3u8",
        "latency": 271,
        "quality": "",
        "stability": 1,
        "type": "hls"
      }
    ]
  },
  {
    "id": "publicmovies",
    "name": "Public Movies",
    "category": "Movies",
    "logo": "https://xstreamcp-assets-msp.streamready.in/assets/LIVETV/LIVECHANNEL/LIVETV_LIVETVCHANNEL_PUBLIC_MOVIES/images/LOGO_HD/image.png",
    "epg_id": "PublicMovies.in@SD",
    "servers": [
      {
        "url": "https://mumt04.tangotv.in/PUBLICMOVIES/index.m3u8",
        "latency": 260,
        "quality": "",
        "stability": 1,
        "type": "hls"
      }
    ]
  },
  {
    "id": "rojamovies",
    "name": "Roja Movies",
    "category": "Movies",
    "logo": "https://jiotvimages.cdn.jio.com/dare_images/images/rojamovies.png",
    "epg_id": "RojaMovies.in@SD",
    "servers": [
      {
        "url": "https://stream.rojatv.cloud/rojatv/rojatv/index.m3u8",
        "latency": 1203,
        "quality": "FHD",
        "stability": 0.9352226720647774,
        "type": "hls"
      }
    ]
  },
  {
    "id": "romedynow",
    "name": "Romedy Now",
    "category": "Movies",
    "logo": "https://xstreamcp-assets-msp.streamready.in/assets/LIVETV/LIVECHANNEL/LIVETV_LIVETVCHANNEL_ROMEDY_NOW/images/LOGO_HD/image.png",
    "epg_id": "RomedyNow.in@SD",
    "servers": [
      {
        "url": "http://116.90.120.151:8000/play/a0is/index.m3u8",
        "latency": 532,
        "quality": "",
        "stability": 1,
        "type": "hls"
      }
    ]
  },
  {
    "id": "sonymax",
    "name": "SONY Max",
    "category": "Movies",
    "logo": "https://xstreamcp-assets-msp.streamready.in/assets/LIVETV/LIVECHANNEL/LIVETV_LIVETVCHANNEL_SONY_MAX/images/LOGO_HD/image.png",
    "epg_id": "SonyMax.in@HD",
    "servers": [
      {
        "url": "http://116.90.120.151:8000/play/a0jf/index.m3u8",
        "latency": 522,
        "quality": "FHD",
        "stability": 1,
        "type": "hls"
      },
      {
        "url": "http://103.99.249.139/sonymax/index.m3u8",
        "latency": 603,
        "quality": "SD",
        "stability": 0.9877049180327869,
        "type": "hls"
      }
    ]
  },
  {
    "id": "sonypix",
    "name": "SONY Pix",
    "category": "Movies",
    "logo": "https://i.postimg.cc/Z5G8j67L/PIX-HD-WHITE.png",
    "epg_id": "SonyPix.in@HD",
    "servers": [
      {
        "url": "http://103.229.254.25:7001/play/a0ed/index.m3u8",
        "latency": 540,
        "quality": "FHD",
        "stability": 0.9554655870445344,
        "type": "hls"
      }
    ]
  },
  {
    "id": "sonywah",
    "name": "SONY Wah",
    "category": "Movies",
    "logo": "https://xstreamcp-assets-msp.streamready.in/assets/LIVETV/LIVECHANNEL/LIVETV_LIVETVCHANNEL_SONY_WAH/images/LOGO_HD/image.png",
    "epg_id": "SonyWah.in@SD",
    "servers": [
      {
        "url": "http://116.90.120.151:8000/play/a0kt/index.m3u8",
        "latency": 516,
        "quality": "",
        "stability": 1,
        "type": "hls"
      }
    ]
  },
  {
    "id": "stargold",
    "name": "STAR Gold",
    "category": "Movies",
    "logo": "https://i.imgur.com/xC460sj.png",
    "epg_id": "StarGold.in@HD",
    "servers": [
      {
        "url": "http://103.229.254.25:7001/play/a0dd/index.m3u8",
        "latency": 540,
        "quality": "FHD",
        "stability": 0.9919028340080972,
        "type": "hls"
      },
      {
        "url": "http://103.99.249.139/stargold/index.m3u8",
        "latency": 607,
        "quality": "HD",
        "stability": 0.9918367346938776,
        "type": "hls"
      },
      {
        "url": "http://103.99.249.139/stargold/tracks-v1a1/mono.m3u8",
        "latency": 664,
        "quality": "",
        "stability": 0.9551020408163265,
        "type": "hls"
      }
    ]
  },
  {
    "id": "stargold2",
    "name": "STAR Gold 2",
    "category": "Movies",
    "logo": "https://i.imgur.com/G0ZfzZr.png",
    "epg_id": "StarGold2.in@SD",
    "servers": [
      {
        "url": "http://116.90.120.151:8000/play/a0gz/index.m3u8",
        "latency": 516,
        "quality": "",
        "stability": 1,
        "type": "hls"
      },
      {
        "url": "http://103.229.254.25:7001/play/a0d0/index.m3u8",
        "latency": 548,
        "quality": "FHD",
        "stability": 0.9878542510121457,
        "type": "hls"
      }
    ]
  },
  {
    "id": "stargoldromance",
    "name": "STAR Gold Romance",
    "category": "Movies",
    "logo": "https://i.imgur.com/gSWv9U3.png",
    "epg_id": "StarGoldRomance.in@SD",
    "servers": [
      {
        "url": "http://116.90.120.151:8000/play/a0he/index.m3u8",
        "latency": 523,
        "quality": "",
        "stability": 1,
        "type": "hls"
      }
    ]
  },
  {
    "id": "stargoldselect",
    "name": "STAR Gold Select",
    "category": "Movies",
    "logo": "https://i.imgur.com/U7eiuqv.png",
    "epg_id": "StarGoldSelect.in@HD",
    "servers": [
      {
        "url": "http://103.229.254.25:7001/play/a032/index.m3u8",
        "latency": 539,
        "quality": "FHD",
        "stability": 0.9635627530364372,
        "type": "hls"
      }
    ]
  },
  {
    "id": "stargoldthrills",
    "name": "STAR Gold Thrills",
    "category": "Movies",
    "logo": "https://i.imgur.com/azqtpYh.png",
    "epg_id": "StarGoldThrills.in@SD",
    "servers": [
      {
        "url": "http://116.90.120.151:8000/play/a0gw/index.m3u8",
        "latency": 517,
        "quality": "",
        "stability": 1,
        "type": "hls"
      }
    ]
  },
  {
    "id": "starmoviesselect",
    "name": "STAR Movies Select",
    "category": "Movies",
    "logo": "https://xstreamcp-assets-msp.streamready.in/assets/LIVETV/LIVECHANNEL/LIVETV_LIVETVCHANNEL_STAR_MOVIES_SELECT_HD/images/LOGO_HD/image.png",
    "epg_id": "StarMoviesSelect.in@HD",
    "servers": [
      {
        "url": "http://116.90.120.151:8000/play/a0ij/index.m3u8",
        "latency": 520,
        "quality": "FHD",
        "stability": 1,
        "type": "hls"
      }
    ]
  },
  {
    "id": "starutsavmovies",
    "name": "STAR Utsav Movies",
    "category": "Movies",
    "logo": "https://i.imgur.com/k5QHfH2.png",
    "epg_id": "StarUtsavMovies.in@SD",
    "servers": [
      {
        "url": "http://116.90.120.151:8000/play/a0ka/index.m3u8",
        "latency": 540,
        "quality": "",
        "stability": 1,
        "type": "hls"
      }
    ]
  },
  {
    "id": "sheemaroobollywood",
    "name": "Sheemaroo Bollywood",
    "category": "Movies",
    "logo": "",
    "servers": [
      {
        "url": "https://cdn-uw2-prod.tsv2.amagi.tv/linear/amg00864-shemarooenterta-shemabollywood-ono/playlist.m3u8",
        "latency": 384,
        "quality": "",
        "stability": 1,
        "type": "hls"
      }
    ]
  },
  {
    "id": "shemaroojosh",
    "name": "Shemaroo Josh",
    "category": "Movies",
    "logo": "https://dtil.tmsimg.com/assets/GNLZZGG00297P3E.png?lock=720x540",
    "epg_id": "ShemarooJosh.in@SD",
    "servers": [
      {
        "url": "https://airtelapp.shemaroo.com/shemarooChumbakTV/smil:shemarooChumbakTVadp.smil/playlist.m3u8",
        "latency": 870,
        "quality": "HD",
        "stability": 1,
        "type": "hls"
      }
    ]
  },
  {
    "id": "shubhcinematv",
    "name": "Shubh Cinema Tv",
    "category": "Movies",
    "logo": "https://i.imgur.com/RQhorAG.png",
    "epg_id": "ShubhCinemaTV.in@SD",
    "servers": [
      {
        "url": "https://d393sxaxig6bax.cloudfront.net/out/v1/589cf2cf44bf42bb941e817a2240d62e/index.m3u8",
        "latency": 661,
        "quality": "HD",
        "stability": 1,
        "type": "hls"
      }
    ]
  },
  {
    "id": "skycinemaanimation",
    "name": "Sky Cinema Animation",
    "category": "Movies",
    "logo": "https://s3.aynaott.com/storage/a6d7d9729aafd5055bfd5356b6fa8eef",
    "servers": [
      {
        "url": "https://tvsen7.aynascope.net/skycinemanimation/index.m3u8?e=1774601296&u=78be6644-0a65-48ec-81a4-089ac65a2619&token=738891a68216e11b2e94d0c901756971",
        "latency": 1165,
        "quality": "",
        "stability": 1,
        "type": "hls"
      }
    ]
  },
  {
    "id": "southmovies",
    "name": "South Movies",
    "category": "Movies",
    "logo": "",
    "servers": [
      {
        "url": "https://live20.bozztv.com/giatvplayout7/giatv-209593/tracks-v1a1/mono.ts.m3u8",
        "latency": 69,
        "quality": "",
        "stability": 0.9183673469387755,
        "type": "hls"
      }
    ]
  },
  {
    "id": "studioone",
    "name": "Studio One",
    "category": "Movies",
    "logo": "https://i.imgur.com/yOPB7JB.png",
    "epg_id": "StudioOnePlus.in@SD",
    "servers": [
      {
        "url": "https://cdn-1.pishow.tv/live/276/master.m3u8",
        "latency": 750,
        "quality": "HD",
        "stability": 0.9959514170040485,
        "type": "hls"
      }
    ]
  },
  {
    "id": "suriyantv",
    "name": "Suriyan Tv",
    "category": "Movies",
    "logo": "https://jiotvimages.cdn.jio.com/dare_images/images/suriyantvtamil.png",
    "epg_id": "SuriyanTV.in@SD",
    "servers": [
      {
        "url": "https://stream.sscloud7.com/live/suriyantv/index.m3u8",
        "latency": 1043,
        "quality": "",
        "stability": 0.9919028340080972,
        "type": "hls"
      }
    ]
  },
  {
    "id": "tensionstv",
    "name": "Tensions Tv",
    "category": "Movies",
    "logo": "https://d229kpbsb5jevy.cloudfront.net/yuppfast/content/common/channel/logos/tensions-tv.png",
    "epg_id": "72",
    "servers": [
      {
        "url": "https://streams2.sofast.tv/ptnr-yupptv/title-TENSIONS-TV-ENG_yupptv/v1/master/611d79b11b77e2f571934fd80ca1413453772ac7/9db01cea-0af6-4382-b2c6-e23525f6640d/manifest.m3u8?hdnts=st%3D1774595536~exp%3D1774617136~acl%3D%21%2A%2Fptnr-yupptv%2Ftitle-TENSIONS-TV-ENG_yupptv%2Fv1%2Fmaster%2F611d79b11b77e2f571934fd80ca1413453772ac7%2F9db01cea-0af6-4382-b2c6-e23525f6640d%2F%2A%21%2Fpayload%2Fyupptvott_5_-1_7c03c72952b44aa4_DE_64.236.201.34_yuppfast_2_channel_72_-1%2F%2A~data%3Dyupptvott_5_-1_7c03c72952b44aa4_DE_64.236.201.34_yuppfast_2_channel_72_-1~hmac%3D9f6eb5a76c41514e1996eab0c28193c0402f75eab50ab62a00761124f92ceafd",
        "latency": 784,
        "quality": "HD",
        "stability": 1,
        "type": "hls"
      }
    ]
  },
  {
    "id": "thalaatv",
    "name": "Thalaa Tv",
    "category": "Movies",
    "logo": "https://d229kpbsb5jevy.cloudfront.net/yuppfast/content/common/channel/logos/thalaa-tv.png",
    "epg_id": "ThalaaTV.in@HD",
    "servers": [
      {
        "url": "https://streams2.sofast.tv/ptnr-yupptv/title-THALAA-TV-TAM_yupptv/v1/master/611d79b11b77e2f571934fd80ca1413453772ac7/2069c593-3c07-4d62-9d44-746be5c3a5d6/manifest.m3u8?hdnts=st%3D1774595505~exp%3D1774617105~acl%3D%21%2A%2Fptnr-yupptv%2Ftitle-THALAA-TV-TAM_yupptv%2Fv1%2Fmaster%2F611d79b11b77e2f571934fd80ca1413453772ac7%2F2069c593-3c07-4d62-9d44-746be5c3a5d6%2F%2A%21%2Fpayload%2Fyupptvott_5_-1_7c03c72952b44aa4_DE_64.236.201.34_yuppfast_2_channel_70_-1%2F%2A~data%3Dyupptvott_5_-1_7c03c72952b44aa4_DE_64.236.201.34_yuppfast_2_channel_70_-1~hmac%3Db67f10aaf4544c7d2b15d4242b98bf060809884ded655c74900b420063f4d438",
        "latency": 696,
        "quality": "HD",
        "stability": 1,
        "type": "hls"
      },
      {
        "url": "https://streams2.sofast.tv/v1/master/611d79b11b77e2f571934fd80ca1413453772ac7/2069c593-3c07-4d62-9d44-746be5c3a5d6/manifest.m3u8",
        "latency": 336,
        "quality": "FHD",
        "stability": 0.8666666666666667,
        "type": "hls"
      }
    ]
  },
  {
    "id": "theexplorers",
    "name": "The Explorers",
    "category": "Movies",
    "logo": "https://d229kpbsb5jevy.cloudfront.net/yuppfast/content/common/channel/logos/ggdzvt.png",
    "epg_id": "88",
    "servers": [
      {
        "url": "https://streams2.sofast.tv/ptnr-yupptv/title-THE-EXPLORERS-ENG_yupptv/v1/master/611d79b11b77e2f571934fd80ca1413453772ac7/4804aca3-dd54-43d1-8caa-0b836a76d9e9/manifest.m3u8?hdnts=st%3D1774595477~exp%3D1774617077~acl%3D%21%2A%2Fptnr-yupptv%2Ftitle-THE-EXPLORERS-ENG_yupptv%2Fv1%2Fmaster%2F611d79b11b77e2f571934fd80ca1413453772ac7%2F4804aca3-dd54-43d1-8caa-0b836a76d9e9%2F%2A%21%2Fpayload%2Fyupptvott_5_-1_7c03c72952b44aa4_DE_64.236.201.34_yuppfast_2_channel_88_-1%2F%2A~data%3Dyupptvott_5_-1_7c03c72952b44aa4_DE_64.236.201.34_yuppfast_2_channel_88_-1~hmac%3Dfd4b9d350e159be69f5d0bebbd455031e6efbd5e55ed2ba1649cddf3fe0ad3c4",
        "latency": 915,
        "quality": "HD",
        "stability": 1,
        "type": "hls"
      }
    ]
  },
  {
    "id": "tollytv",
    "name": "Tolly Tv",
    "category": "Movies",
    "logo": "https://d229kpbsb5jevy.cloudfront.net/yuppfast/content/common/channel/logos/aumnrs.png",
    "epg_id": "TollyTV.in@HD",
    "servers": [
      {
        "url": "https://streams2.sofast.tv/ptnr-yupptv/title-TOLLY-TV-TEL_yupptv/v1/master/611d79b11b77e2f571934fd80ca1413453772ac7/13b5735d-52c3-4be0-853d-e0ec0127e708/manifest.m3u8?hdnts=st%3D1774595539~exp%3D1774617139~acl%3D%21%2A%2Fptnr-yupptv%2Ftitle-TOLLY-TV-TEL_yupptv%2Fv1%2Fmaster%2F611d79b11b77e2f571934fd80ca1413453772ac7%2F13b5735d-52c3-4be0-853d-e0ec0127e708%2F%2A%21%2Fpayload%2Fyupptvott_5_-1_7c03c72952b44aa4_DE_64.236.201.34_yuppfast_2_channel_92_-1%2F%2A~data%3Dyupptvott_5_-1_7c03c72952b44aa4_DE_64.236.201.34_yuppfast_2_channel_92_-1~hmac%3D859c66232a4735fc66d3c158128da0c37785d0cdc110a5000142b2fe8730ab61",
        "latency": 499,
        "quality": "HD",
        "stability": 1,
        "type": "hls"
      },
      {
        "url": "https://streams2.sofast.tv/v1/master/611d79b11b77e2f571934fd80ca1413453772ac7/13b5735d-52c3-4be0-853d-e0ec0127e708/manifest.m3u8",
        "latency": 340,
        "quality": "FHD",
        "stability": 0.8888888888888888,
        "type": "hls"
      }
    ]
  },
  {
    "id": "urbanaction",
    "name": "Urban Action",
    "category": "Movies",
    "logo": "https://d229kpbsb5jevy.cloudfront.net/yuppfast/content/common/channel/logos/urban-action.png",
    "epg_id": "60",
    "servers": [
      {
        "url": "https://streams2.sofast.tv/ptnr-yupptv/title-URBAN-ACTION-ENG_yupptv/v1/master/611d79b11b77e2f571934fd80ca1413453772ac7/7ad8ce96-5a3f-413e-ae15-7c2cef7bc8f8/manifest.m3u8?hdnts=st%3D1774595476~exp%3D1774617076~acl%3D%21%2A%2Fptnr-yupptv%2Ftitle-URBAN-ACTION-ENG_yupptv%2Fv1%2Fmaster%2F611d79b11b77e2f571934fd80ca1413453772ac7%2F7ad8ce96-5a3f-413e-ae15-7c2cef7bc8f8%2F%2A%21%2Fpayload%2Fyupptvott_5_-1_7c03c72952b44aa4_DE_64.236.201.34_yuppfast_2_channel_60_-1%2F%2A~data%3Dyupptvott_5_-1_7c03c72952b44aa4_DE_64.236.201.34_yuppfast_2_channel_60_-1~hmac%3Db0c2cf532444f2237653518ab7a4f2ec2ff45fc04f0af6b57481da5fb163c3f2",
        "latency": 257,
        "quality": "HD",
        "stability": 1,
        "type": "hls"
      }
    ]
  },
  {
    "id": "weshort",
    "name": "Weshort",
    "category": "Movies",
    "logo": "https://d229kpbsb5jevy.cloudfront.net/yuppfast/content/common/channel/logos/weshort.png",
    "epg_id": "57",
    "servers": [
      {
        "url": "https://streams2.sofast.tv/ptnr-yupptv/title-WESHORT-ENG_yupptv/v1/master/611d79b11b77e2f571934fd80ca1413453772ac7/ea019bed-a45e-4dfe-a452-84f5f2f76ea9/manifest.m3u8?hdnts=st%3D1774595537~exp%3D1774617137~acl%3D%21%2A%2Fptnr-yupptv%2Ftitle-WESHORT-ENG_yupptv%2Fv1%2Fmaster%2F611d79b11b77e2f571934fd80ca1413453772ac7%2Fea019bed-a45e-4dfe-a452-84f5f2f76ea9%2F%2A%21%2Fpayload%2Fyupptvott_5_-1_7c03c72952b44aa4_DE_64.236.201.34_yuppfast_2_channel_57_-1%2F%2A~data%3Dyupptvott_5_-1_7c03c72952b44aa4_DE_64.236.201.34_yuppfast_2_channel_57_-1~hmac%3D1763f8b1e0f45038530c91039ff76f4eaba5e58e61fffbfe5f267b14edf7c27a",
        "latency": 383,
        "quality": "HD",
        "stability": 1,
        "type": "hls"
      }
    ]
  },
  {
    "id": "zeeaction",
    "name": "ZEE Action",
    "category": "Movies",
    "logo": "",
    "servers": [
      {
        "url": "http://103.175.73.12:8080/live/270/270_0.m3u8",
        "latency": 468,
        "quality": "",
        "stability": 1,
        "type": "hls"
      }
    ]
  },
  {
    "id": "zeeanmoltv",
    "name": "ZEE Anmol Tv",
    "category": "Movies",
    "logo": "",
    "servers": [
      {
        "url": "http://103.175.73.12:8080/live/256/256_0.m3u8",
        "latency": 460,
        "quality": "",
        "stability": 1,
        "type": "hls"
      }
    ]
  },
  {
    "id": "zeebiskope",
    "name": "ZEE Biskope",
    "category": "Movies",
    "logo": "https://xstreamcp-assets-msp.streamready.in/assets/LIVETV/LIVECHANNEL/LIVETV_LIVETVCHANNEL_ZEE_BISKOPE/images/LOGO_HD/LOGO_HD_image.png",
    "epg_id": "ZeeBiskope.in@SD",
    "servers": [
      {
        "url": "http://116.90.120.151:8000/play/a0kf/index.m3u8",
        "latency": 528,
        "quality": "",
        "stability": 1,
        "type": "hls"
      }
    ]
  },
  {
    "id": "zeecinema",
    "name": "ZEE Cinema",
    "category": "Movies",
    "logo": "https://xstreamcp-assets-msp.streamready.in/assets/LIVETV/LIVECHANNEL/LIVETV_LIVETVCHANNEL_ZEE_CINEMA/images/LOGO_HD/LOGO_HD_image.png",
    "epg_id": "ZeeCinema.in@HD",
    "servers": [
      {
        "url": "http://103.99.249.139/zeecinema/index.m3u8",
        "latency": 1365,
        "quality": "HD",
        "stability": 0.9838056680161943,
        "type": "hls"
      }
    ]
  },
  {
    "id": "zeetalkies",
    "name": "ZEE Talkies",
    "category": "Movies",
    "logo": "https://xstreamcp-assets-msp.streamready.in/assets/LIVETV/LIVECHANNEL/LIVETV_LIVETVCHANNEL_ZEE_TALKIES/images/LOGO_HD/LOGO_HD_image.png",
    "epg_id": "ZeeTalkies.in@HD",
    "servers": [
      {
        "url": "http://116.90.120.151:8000/play/a0io/index.m3u8",
        "latency": 521,
        "quality": "FHD",
        "stability": 1,
        "type": "hls"
      }
    ]
  },
  {
    "id": "zbcinema",
    "name": "Zb Cinema",
    "category": "Movies",
    "logo": "https://jiotvimages.cdn.jio.com/dare_images/images/ZBCINEMA.png",
    "epg_id": "ZBCinema.in@HD",
    "servers": [
      {
        "url": "https://server.zillarbarta.com/ZBCINEMA/tracks-v1a1/mono.ts.m3u8",
        "latency": 254,
        "quality": "",
        "stability": 0.8823529411764706,
        "type": "hls"
      },
      {
        "url": "https://server.zillarbarta.com/ZBCINEMA/index.m3u8",
        "latency": 896,
        "quality": "HD",
        "stability": 0.8097165991902834,
        "type": "hls"
      }
    ]
  }
]
